LICENSE.txt
README.md
pyproject.toml
setup.py
src/dj_init.egg-info/PKG-INFO
src/dj_init.egg-info/SOURCES.txt
src/dj_init.egg-info/dependency_links.txt
src/dj_init.egg-info/entry_points.txt
src/dj_init.egg-info/requires.txt
src/dj_init.egg-info/top_level.txt
src/djinit/__init__.py
src/djinit/index.py
src/djinit/utilities/__init__.py
src/djinit/utilities/autoopen.py
src/djinit/utilities/project.py
src/djinit/utilities/settings.py
src/djinit/utilities/urls.py
src/djinit/utilities/views.py
src/djinit/utilities/templates/index.html
src/djinit/utilities/templates/app/page.html
src/djinit/utilities/templates/includes/footer.html
src/djinit/utilities/templates/includes/header.html
src/djinit/utilities/templates/includes/sidebar.html
src/djinit/utilities/templates/layouts/base.html
src/djinit/utilities/templates/partials/_css.html
src/djinit/utilities/templates/partials/_js.html
src/djinit/utilities/templates/partials/_pagination.html
src/djinit/utilities/templates/partials/_swal.html